bib/__init__.py
bib/config_default.yaml
bibcli-0.0.3.dist-info/LICENSE.txt
bibcli-0.0.3.dist-info/METADATA
bibcli-0.0.3.dist-info/WHEEL
bibcli-0.0.3.dist-info/entry_points.txt
bibcli-0.0.3.dist-info/top_level.txt
bibcli-0.0.3.dist-info/RECORD
