Metadata-Version: 2.1
Name: bibcli
Version: 0.0.3
Summary: Command line bibliography manager
Home-page: https://gitlab.com/juanmeleiro/bib
Author: Juan Meleiro
Author-email: juan.meleiro@me.com
License: GPLv3+
Platform: UNKNOWN
Classifier: Development Status :: 2 - Pre-Alpha
Classifier: Environment :: Console
Classifier: License :: OSI Approved :: GNU General Public License v3 or later (GPLv3+)
Classifier: Programming Language :: Python :: 3
Classifier: Intended Audience :: Science/Research
Requires-Dist: argparse
Requires-Dist: bibtexparser
Requires-Dist: termcolor
